Verilas/Ex C/ex_c.v
module alarme(p,w,m,s,a);
    input p,w,m,s; 
    output reg a;

    always @ (p or w or m or s) begin
        a = m | (s & (p | w));
    end
endmodule

Verilas/Ex C/ex_c_tb.v
`timescale 1ns/1ns
`include "ex_c.v"

module ex_c_tb;

    reg p,w,m,s;
    wire a;
    alarme uut(p,w,m,s,a);

    initial begin
        $dumpfile("ex_c_tb.vcd");
        $dumpvars(0,ex_c_tb);
        p = 0; //0000
        w = 0;
        m = 0;
        s = 0; #20;

        p = 0; //0001
        w = 0;
        m = 0;
        s = 1; #20;

        p = 0; //0010
        w = 0;
        m = 1;
        s = 0; #20;

        p = 0; //0011
        w = 0;
        m = 1;
        s = 1; #20;

        p = 0; //0100
        w = 1;
        m = 0;
        s = 0; #20;

        p = 0; //0101
        w = 1;
        m = 0;
        s = 1; #20;

        p = 0; //0110
        w = 1;
        m = 1;
        s = 0; #20;

        p = 0; //0111
        w = 1;
        m = 1;
        s = 1; #20;

        p = 1; //1000
        w = 0;
        m = 0;
        s = 0; #20;

        p = 1; //1001
        w = 0;
        m = 0;
        s = 1; #20;

        p = 1; //1010
        w = 0;
        m = 1;
        s = 0; #20;

        p = 1; //1011
        w = 0;
        m = 1;
        s = 1; #20;

        p = 1; //1100
        w = 1;
        m = 0;
        s = 0; #20;

        p = 1; //1101
        w = 1;
        m = 0;
        s = 1; #20;

        p = 1; //1110
        w = 1;
        m = 1;
        s = 0; #20;

        p = 1; //1111
        w = 1;
        m = 1;
        s = 1; #20;

        $display("Teste completo");
    end
endmodule

Verilas/Ex C/ex_c_tb.vcd
$date
	Mon Sep 09 10:09:53 2024
$end
$version
	Icarus Verilog
$end
$timescale
	1ns
$end
$scope module ex_c_tb $end
$var wire 1 ! a $end
$var reg 1 " m $end
$var reg 1 # p $end
$var reg 1 $ s $end
$var reg 1 % w $end
$scope module uut $end
$var wire 1 " m $end
$var wire 1 # p $end
$var wire 1 $ s $end
$var wire 1 % w $end
$var reg 1 ! a $end
$upscope $end
$upscope $end
$enddefinitions $end
$comment Show the parameter values. $end
$dumpall
$end
#0
$dumpvars
0%
0$
0#
0"
0!
$end
#20
1$
#40
1!
0$
1"
#60
1$
#80
0!
0$
0"
1%
#100
1!
1$
#120
0$
1"
#140
1$
#160
0!
0$
0"
0%
1#
#180
1!
1$
#200
0$
1"
#220
1$
#240
0!
0$
0"
1%
#260
1!
1$
#280
0$
1"
#300
1$
