codigos e exercicios/Exercicios combinacionais/Ex B/ex_b.v
module amplificador(a,b,c,tv,cpu,alexa);
    input a,b,c;
    output reg tv,cpu,alexa;

    always @ (a or b or c) begin

    tv = a;
    cpu = ~a & b;
    alexa = ~a & ~b & c;
    end

endmodule

codigos e exercicios/Exercicios combinacionais/Ex B/ex_b_tb.v
`timescale 1ns/1ns
`include "ex_b.v"

module ex_b_tb;

    reg a, b,c;
    wire tv,cpu,alexa;
    amplificador uut(a,b,c,tv,cpu,alexa);

    initial begin
        $dumpfile("ex_b_tb.vcd");
        $dumpvars(0,ex_b_tb);
        a = 0;
        b = 0;
        c = 0; #20;
        a = 0; 
        b = 0;
        c = 1; #20;
        a = 0;
        b = 1;
        c = 0; #20;
        a = 0;
        b = 1;
        c = 1; #20;
        a = 1;
        b = 0;
        c = 0; #20;
        a = 1;
        b = 0;
        c = 1; #20;
        a = 1;
        b = 1;
        c = 0; #20;
        a = 1;
        b = 1;
        c = 1; #20;
        $display("Teste completo");
    end
endmodule

codigos e exercicios/Exercicios combinacionais/Ex B/ex_b_tb.vcd
$date
	Mon Sep 09 09:26:26 2024
$end
$version
	Icarus Verilog
$end
$timescale
	1ns
$end
$scope module ex_b_tb $end
$var wire 1 ! tv $end
$var wire 1 " cpu $end
$var wire 1 # alexa $end
$var reg 1 $ a $end
$var reg 1 % b $end
$var reg 1 & c $end
$scope module uut $end
$var wire 1 $ a $end
$var wire 1 % b $end
$var wire 1 & c $end
$var reg 1 # alexa $end
$var reg 1 " cpu $end
$var reg 1 ! tv $end
$upscope $end
$upscope $end
$enddefinitions $end
$comment Show the parameter values. $end
$dumpall
$end
#0
$dumpvars
0&
0%
0$
0#
0"
0!
$end
#20
1#
1&
#40
0#
1"
0&
1%
#60
1&
#80
0"
1!
0&
0%
1$
#100
1&
#120
0&
1%
#140
1&
