codigos e exercicios/Contador Registrador/contador assincrono/FF_JK.v
module FF_JK(j,k,pr,clr,q,nq,clk);
    input j,k,pr,clr,clk;
    output reg q,nq;

    always@ (negedge clk or clr) begin
        if ({pr,clr} == 2'b10)begin
            q = 1'b0;
            nq = ~q;
        end
        else if({pr,clr} == 2'b01)begin
            q = 1'b1;
            nq = ~q;
        end
        else if({pr,clr} == 2'b00) begin
            q = 1'bx;
            nq = 1'bx;
        end
        else begin
            case({j,k})
                2'b00:begin
                    q = q; nq = nq;
                end
                2'b01: begin
                    q = 0; nq = ~q;
                end
                2'b10: begin
                    q = 1; nq = ~q;
                end
                2'b11: q = ~q;
                default: q = 0;
            endcase
        end
    end
endmodule

codigos e exercicios/Flip Flops/FF_JK/FF_JK_tb.v
`timescale 1ns/1ns
`include "FF_JK.v"

module FF_JK_tb;
    reg j,k,pr,clr,clk;
    wire q,nq;
    FF_JK uut(j,k,pr,clr,q,nq,clk);

    initial begin
        $dumpfile("FF_JK_tb.vcd");
        $dumpvars(1);
        pr = 1; clr = 0; #20;
        pr = 1; clr = 1; j = 0; k = 0; #20;
        j = 0; k = 1; #20;
        j = 1; k = 0; #20;
        j = 1; k = 1; #20;
        $display("Teste completo");
        $finish;
    end

    initial begin
        clk = 0;
        forever #10 clk = ~ clk;
    end
endmodule

codigos e exercicios/Flip Flops/FF_JK/FF_JK_tb.vcd
$date
	Mon Oct 21 08:56:28 2024
$end
$version
	Icarus Verilog
$end
$timescale
	1ns
$end
$scope module FF_JK_tb $end
$var wire 1 ! q $end
$var wire 1 " nq $end
$var reg 1 # clk $end
$var reg 1 $ clr $end
$var reg 1 % j $end
$var reg 1 & k $end
$var reg 1 ' pr $end
$upscope $end
$enddefinitions $end
$comment Show the parameter values. $end
$dumpall
$end
#0
$dumpvars
1'
x&
x%
0$
0#
x"
x!
$end
#10
1"
0!
1#
#20
0#
0&
0%
1$
#30
1#
#40
0#
1&
#50
1#
#60
0#
0&
1%
#70
0"
1!
1#
#80
0#
1&
#90
0!
1#
