codigos e exercicios/Maquina de Estados Finito/morse.v
module morse (
    in, out, reset, clk
);
    input in, reset, clk;
    output reg [7:0] out;

    parameter IDLE = 5'bxxxxx, E = 5'b00000, A = 5'b00001, T = 5'b00010, I = 5'b00100, U = 5'B00101, S = 5'b00110, R = 5'b00111, W = 5'b01000, L = 5'b10001, P = 5'b10010, J = 5'b10011;
    reg [5:0] state, next_state;

    // Lógica Sequencial    
    always @(posedge clk) begin
        if (reset)
            state = IDLE;
        else
            state = next_state;        
    end
    
    // Lógica Combinacional de entrada
    always @(*) begin
        case (state)   // 1 -> ponto 0 -> traço
            IDLE: begin
                if (in)
                    next_state = E; // .
                else
                    next_state = T; // -
            end
            E: begin
                if (in)
                    next_state = I; // ..
                else
                    next_state = A; // .-
            end           
            A: begin
                if (in)
                    next_state = R; // .-.
                else
                    next_state = W; // .--
            end
            I: begin
                if (in)
                    next_state = S; // ...
                else
                    next_state = U; // ..-
            end
            R: begin
                if (in)
                    next_state = IDLE; // FIM
                else
                    next_state = L; // .-..
            end
            W: begin
                if (in)
                    next_state = P; // .--.
                else
                    next_state = J; // .---
            end
            default: next_state = IDLE;
        endcase
    end

    // Lógica Combinacional de saída
    always @(*) begin
        case (state)
            IDLE: out = 8'h00;
            E: out = 8'h45;
            T: out = 8'h54;
            A: out = 8'h42;
            I: out = 8'h49;
            R: out = 8'h52;
            W: out = 8'h57;
            U: out = 8'h55;
            S: out = 8'h53;
            L: out = 8'h4C;
            P: out = 8'h50;
            J: out = 8'h4A;
            default: next_state = IDLE;
        endcase
    end
endmodule

codigos e exercicios/Maquina de Estados Finito/morse_tb.v
`timescale 10ns/1ns
`include "morse.v"

module morse_tb;


    reg in, reset, clk;
    wire [7:0] out;
    morse uut(in, out, reset, clk);

    initial begin
        $dumpfile("morse.vcd");
        $dumpvars(0, morse_tb);

        reset = 1; #15;
        reset = 0; #10;
        in = 1; #50;
        reset = 1; #15;
        reset = 0;

        in = 1; #50;
        in = 0; #15;
        reset = 1; #15;
        reset = 0;

        in = 1; #90;
        reset = 1; #15;
        reset = 0;
        $finish;
    end

    initial begin
        clk = 0;
        forever #10 clk = ~clk;
    end
    

endmodule

codigos e exercicios/Maquina de Estados Finito/morse.vcd
$date
	Mon Nov 18 09:47:13 2024
$end
$version
	Icarus Verilog
$end
$timescale
	1ns
$end
$scope module morse_tb $end
$var wire 8 ! out [7:0] $end
$var reg 1 " clk $end
$var reg 1 # in $end
$var reg 1 $ reset $end
$scope module uut $end
$var wire 1 " clk $end
$var wire 1 # in $end
$var wire 1 $ reset $end
$var parameter 5 % A $end
$var parameter 5 & E $end
$var parameter 5 ' I $end
$var parameter 5 ( IDLE $end
$var parameter 5 ) J $end
$var parameter 5 * L $end
$var parameter 5 + P $end
$var parameter 5 , R $end
$var parameter 5 - S $end
$var parameter 5 . T $end
$var parameter 5 / U $end
$var parameter 5 0 W $end
$var reg 6 1 next_state [5:0] $end
$var reg 8 2 out [7:0] $end
$var reg 6 3 state [5:0] $end
$upscope $end
$upscope $end
$enddefinitions $end
$comment Show the parameter values. $end
$dumpall
b1000 0
b101 /
b10 .
b110 -
b111 ,
b10010 +
b10001 *
b10011 )
bx (
b100 '
b0 &
b1 %
$end
#0
$dumpvars
bx 3
bx 2
bx 1
1$
x#
0"
bx !
$end
#100
b0 !
b0 2
b10 1
b0xxxxx 3
1"
#150
0$
#200
0"
#250
b0 1
1#
#300
b1000101 !
b1000101 2
b100 1
b0 3
1"
#400
0"
#500
b1001001 !
b1001001 2
b110 1
b100 3
1"
#600
0"
#700
b1010011 !
b1010011 2
b0xxxxx 1
b110 3
1"
#750
1$
#800
0"
#900
b0 !
b0 2
b0 1
b0xxxxx 3
1"
0$
#1000
0"
#1100
b1000101 !
b1000101 2
b100 1
b0 3
1"
#1200
0"
#1300
b1001001 !
b1001001 2
b110 1
b100 3
1"
#1400
b101 1
0"
0#
#1500
b1010101 !
b1010101 2
b0xxxxx 1
b101 3
1"
#1550
1$
#1600
0"
#1700
b0 !
b0 2
b0 1
b0xxxxx 3
1"
1#
0$
#1800
0"
#1900
b1000101 !
b1000101 2
b100 1
b0 3
1"
#2000
0"
#2100
b1001001 !
b1001001 2
b110 1
b100 3
1"
#2200
0"
#2300
b1010011 !
b1010011 2
b0xxxxx 1
b110 3
1"
#2400
0"
#2500
b0 !
b0 2
b0 1
b0xxxxx 3
1"
#2600
0"
1$
#2700
1"
#2750
0$
