codigos e exercicios/codificador/codificador.v
module codificador(bcd,y);
    input [3:0] bcd;
    output reg [7:0] y;

    always@ (bcd) begin
        case(bcd)
        4'b0000: y = 8'b11111100; // 0
        4'b0001: y = 8'b01100000; // 1
        4'b0010: y = 8'b11011010; // 2
        4'b0011: y = 8'b11110010; // 3
        4'b0100: y = 8'b01100110; // 4
        4'b0101: y = 8'b10110110; // 5
        4'b0110: y = 8'b10111110; // 6
        4'b0111: y = 8'b11100000; // 7
        4'b1000: y = 8'b11111110; // 8
        4'b1001: y = 8'b11110110; // 9
        4'b1010: y = 8'b11101110; // A
        4'b1011: y = 8'b00111110; // B
        4'b1100: y = 8'b10011100; // C
        4'b1101: y = 8'b01111010; // D
        4'b1110: y = 8'b10011110; // E
        4'b1111: y = 8'b10001110; // F
        default: y = 8'b00000000; // Invalid BCD
        endcase
    end
endmodule

codigos e exercicios/codificador/codificador_tb.v
`timescale 1ns/1ns
`include "codificador.v"

module codificador_tb;

    reg [3:0] bcd;
    wire [7:0] y;
    codificador uut(bcd,y);

    initial begin
        $dumpfile("codificador_tb.vcd");
        $dumpvars(0,codificador_tb);

        bcd = 4'b0000; #20; bcd = 4'b0001; #20;
        bcd = 4'b0010; #20; bcd = 4'b0011; #20;
        bcd = 4'b0100; #20; bcd = 4'b0101; #20;
        bcd = 4'b0110; #20; bcd = 4'b0111; #20;
        bcd = 4'b1000; #20; bcd = 4'b1001; #20;
        bcd = 4'b1010; #20; bcd = 4'b1011; #20;
        bcd = 4'b1100; #20; bcd = 4'b1101; #20;
        bcd = 4'b1110; #20; bcd = 4'b1111; #20;

        $display("teste completo.");
    end
endmodule

codigos e exercicios/codificador/codificador_tb.vcd
$date
	Mon Sep 23 08:21:51 2024
$end
$version
	Icarus Verilog
$end
$timescale
	1ns
$end
$scope module codificador_tb $end
$var wire 8 ! y [7:0] $end
$var reg 4 " bcd [3:0] $end
$scope module uut $end
$var wire 4 # bcd [3:0] $end
$var reg 8 $ y [7:0] $end
$upscope $end
$upscope $end
$enddefinitions $end
$comment Show the parameter values. $end
$dumpall
$end
#0
$dumpvars
b11111100 $
b0 #
b0 "
b11111100 !
$end
#20
b1100000 !
b1100000 $
b1 "
b1 #
#40
b11011010 !
b11011010 $
b10 "
b10 #
#60
b11110010 !
b11110010 $
b11 "
b11 #
#80
b1100110 !
b1100110 $
b100 "
b100 #
#100
b10110110 !
b10110110 $
b101 "
b101 #
#120
b10111110 !
b10111110 $
b110 "
b110 #
#140
b11100000 !
b11100000 $
b111 "
b111 #
#160
b11111110 !
b11111110 $
b1000 "
b1000 #
#180
b11110110 !
b11110110 $
b1001 "
b1001 #
#200
b11101110 !
b11101110 $
b1010 "
b1010 #
#220
b111110 !
b111110 $
b1011 "
b1011 #
#240
b10011100 !
b10011100 $
b1100 "
b1100 #
#260
b1111010 !
b1111010 $
b1101 "
b1101 #
#280
b10011110 !
b10011110 $
b1110 "
b1110 #
#300
b10001110 !
b10001110 $
b1111 "
b1111 #
