codigos e exercicios/Contador Registrador/contador sincrono/crescente/contador_sincrono.v
module contador_sincrono(q,clr,clk);
    input clr,clk;
    output reg [3:0] q;
    always@ (posedge clk) begin
        if(clr == 1'b1)
            q = 4'b0000;

        q = q + 1'b1;
    end
endmodule

codigos e exercicios/Contador Registrador/contador sincrono/crescente/contador_sincrono_tb.v
`timescale 1ns/1ns
`include "contador_sincrono.v"

module contador_sincrono_tb();
    reg clr,clk;
    wire [3:0] q;
    contador_sincrono uut(q,clr,clk);

    initial begin
        $dumpfile("contador_sincrono_tb.vcd");
        $dumpvars(1);
        clr = 1; #20;
        clr = 0;
        #600;

        $display("Teste completo");
        $finish;
    end

    initial begin
        clk = 0;
        forever #10 clk = ~ clk;
    end
endmodule

codigos e exercicios/Contador Registrador/contador sincrono/crescente/contador_sincrono_tb.vcd
$date
	Mon Oct 28 09:29:19 2024
$end
$version
	Icarus Verilog
$end
$timescale
	1ns
$end
$scope module contador_sincrono_tb $end
$var wire 4 ! q [3:0] $end
$var reg 1 " clk $end
$var reg 1 # clr $end
$upscope $end
$enddefinitions $end
$comment Show the parameter values. $end
$dumpall
$end
#0
$dumpvars
1#
0"
bx !
$end
#10
b1 !
1"
#20
0"
0#
#30
b10 !
1"
#40
0"
#50
b11 !
1"
#60
0"
#70
b100 !
1"
#80
0"
#90
b101 !
1"
#100
0"
#110
b110 !
1"
#120
0"
#130
b111 !
1"
#140
0"
#150
b1000 !
1"
#160
0"
#170
b1001 !
1"
#180
0"
#190
b1010 !
1"
#200
0"
#210
b1011 !
1"
#220
0"
#230
b1100 !
1"
#240
0"
#250
b1101 !
1"
#260
0"
#270
b1110 !
1"
#280
0"
#290
b1111 !
1"
#300
0"
#310
b0 !
1"
#320
0"
#330
b1 !
1"
#340
0"
#350
b10 !
1"
#360
0"
#370
b11 !
1"
#380
0"
#390
b100 !
1"
#400
0"
#410
b101 !
1"
#420
0"
#430
b110 !
1"
#440
0"
#450
b111 !
1"
#460
0"
#470
b1000 !
1"
#480
0"
#490
b1001 !
1"
#500
0"
#510
b1010 !
1"
#520
0"
#530
b1011 !
1"
#540
0"
#550
b1100 !
1"
#560
0"
#570
b1101 !
1"
#580
0"
#590
b1110 !
1"
#600
0"
#610
b1111 !
1"
