codigos e exercicios/Contador Registrador/contador assincrono/FF_JK.v
module FF_JK(j,k,pr,clr,q,nq,clk);
    input j,k,pr,clr,clk;
    output reg q,nq;

    always@ (negedge clk or clr) begin
        if ({pr,clr} == 2'b10)begin
            q = 1'b0;
            nq = ~q;
        end
        else if({pr,clr} == 2'b01)begin
            q = 1'b1;
            nq = ~q;
        end
        else if({pr,clr} == 2'b00) begin
            q = 1'bx;
            nq = 1'bx;
        end
        else begin
            case({j,k})
                2'b00:begin
                    q = q; nq = nq;
                end
                2'b01: begin
                    q = 0; nq = ~q;
                end
                2'b10: begin
                    q = 1; nq = ~q;
                end
                2'b11: q = ~q;
                default: q = 0;
            endcase
        end
    end
endmodule

codigos e exercicios/Contador Registrador/contador assincrono/contador_assincrono.v
`include "FF_JK.v"

module contador_assincrono(t,clr,q,clk);
    input t,clr,clk;
    output [3:0] q;
    output nq;

    FF_JK ff1(t,t,1'b1,clr,q[0],nq,clk);
    FF_JK ff2(t,t,1'b1,clr,q[1],nq,q[0]);
    FF_JK ff3(t,t,1'b1,clr,q[2],nq,q[1]);
    FF_JK ff4(t,t,1'b1,clr,q[3],nq,q[2]);
endmodule

codigos e exercicios/Contador Registrador/contador assincrono/contador_assincrono_tb.v
`timescale 1ns/1ns
`include "contador_assincrono.v"

module contador_assincrono_tb;
    reg t,clr,clk;
    wire [3:0] q;
    contador_assincrono uut(t,clr,q,clk);

    initial begin
        $dumpfile("contador_assincrono_tb.vcd");
        $dumpvars(1);
        clr = 1; #20;
        t = 1; #320;

        $display("Teste completo");
        $finish;
    end

    initial begin
        clk = 0;
        forever #10 clk = ~ clk;
    end
endmodule

codigos e exercicios/Contador Registrador/contador assincrono/contador_assincrono_tb.vcd
$date
	Mon Oct 28 08:52:58 2024
$end
$version
	Icarus Verilog
$end
$timescale
	1ns
$end
$scope module contador_assincrono_tb $end
$var wire 4 ! q [3:0] $end
$var reg 1 " clk $end
$var reg 1 # clr $end
$var reg 1 $ t $end
$upscope $end
$enddefinitions $end
$comment Show the parameter values. $end
$dumpall
$end
#0
$dumpvars
x$
1#
0"
b0 !
$end
#10
1"
#20
b1 !
0"
1$
#30
1"
#40
b10 !
0"
#50
1"
#60
b11 !
0"
#70
1"
#80
b100 !
0"
#90
1"
#100
b101 !
0"
#110
1"
#120
b110 !
0"
#130
1"
#140
b111 !
0"
#150
1"
#160
b1000 !
0"
#170
1"
#180
b1001 !
0"
#190
1"
#200
b1010 !
0"
#210
1"
#220
b1011 !
0"
#230
1"
#240
b1100 !
0"
#250
1"
#260
b1101 !
0"
#270
1"
#280
b1110 !
0"
#290
1"
#300
b1111 !
0"
#310
1"
#320
b0 !
0"
#330
1"
#340
b1 !
0"
